{
    "os": "Linux-5.15.0-117-generic-x86_64-with-glibc2.31",
    "python": "3.10.14",
    "heartbeatAt": "2024-07-31T02:34:53.782000",
    "startedAt": "2024-07-31T02:34:53.115829",
    "docker": null,
    "cuda": null,
    "args": [],
    "state": "running",
    "program": "<python with no main file>",
    "codePathLocal": null,
    "git": {
        "remote": "https://github.com/yk-Jeong/iMORS",
        "commit": "7eae808dcb92078ace6bec31dd101300e55ece7b"
    },
    "email": "ykjeong.info@gmail.com",
    "root": "/home/ykjeong/new-repo",
    "host": "mdhiai-ai",
    "username": "ykjeong",
    "executable": "/home/mdhi/anaconda3/envs/predict/bin/python",
    "cpu_count": 14,
    "cpu_count_logical": 28,
    "cpu_freq": {
        "current": 3484.1789642857143,
        "min": 1200.0,
        "max": 4642.857142857143
    },
    "cpu_freq_per_core": [
        {
            "current": 3142.426,
            "min": 1200.0,
            "max": 4800.0
        },
        {
            "current": 4183.846,
            "min": 1200.0,
            "max": 4600.0
        },
        {
            "current": 3300.0,
            "min": 1200.0,
            "max": 4600.0
        },
        {
            "current": 4186.747,
            "min": 1200.0,
            "max": 4600.0
        },
        {
            "current": 3300.0,
            "min": 1200.0,
            "max": 4600.0
        },
        {
            "current": 3300.0,
            "min": 1200.0,
            "max": 4600.0
        },
        {
            "current": 3300.0,
            "min": 1200.0,
            "max": 4600.0
        },
        {
            "current": 3300.0,
            "min": 1200.0,
            "max": 4600.0
        },
        {
            "current": 3300.0,
            "min": 1200.0,
            "max": 4600.0
        },
        {
            "current": 4220.888,
            "min": 1200.0,
            "max": 4700.0
        },
        {
            "current": 4222.524,
            "min": 1200.0,
            "max": 4800.0
        },
        {
            "current": 4184.5,
            "min": 1200.0,
            "max": 4700.0
        },
        {
            "current": 3300.0,
            "min": 1200.0,
            "max": 4600.0
        },
        {
            "current": 3300.0,
            "min": 1200.0,
            "max": 4600.0
        },
        {
            "current": 3300.0,
            "min": 1200.0,
            "max": 4800.0
        },
        {
            "current": 3300.0,
            "min": 1200.0,
            "max": 4600.0
        },
        {
            "current": 3300.0,
            "min": 1200.0,
            "max": 4600.0
        },
        {
            "current": 3300.0,
            "min": 1200.0,
            "max": 4600.0
        },
        {
            "current": 3300.0,
            "min": 1200.0,
            "max": 4600.0
        },
        {
            "current": 1255.643,
            "min": 1200.0,
            "max": 4600.0
        },
        {
            "current": 3300.0,
            "min": 1200.0,
            "max": 4600.0
        },
        {
            "current": 3300.0,
            "min": 1200.0,
            "max": 4600.0
        },
        {
            "current": 3300.0,
            "min": 1200.0,
            "max": 4600.0
        },
        {
            "current": 4116.08,
            "min": 1200.0,
            "max": 4700.0
        },
        {
            "current": 3300.0,
            "min": 1200.0,
            "max": 4800.0
        },
        {
            "current": 3300.0,
            "min": 1200.0,
            "max": 4700.0
        },
        {
            "current": 3300.0,
            "min": 1200.0,
            "max": 4600.0
        },
        {
            "current": 3300.0,
            "min": 1200.0,
            "max": 4600.0
        }
    ],
    "disk": {
        "/": {
            "total": 915.3223114013672,
            "used": 280.37554931640625
        }
    },
    "gpu": "NVIDIA GeForce RTX 3090",
    "gpu_count": 2,
    "gpu_devices": [
        {
            "name": "NVIDIA GeForce RTX 3090",
            "memory_total": 25769803776
        },
        {
            "name": "NVIDIA GeForce RTX 3090",
            "memory_total": 25769803776
        }
    ],
    "memory": {
        "total": 93.99881744384766
    }
}
